pip_safe/__about__.py
pip_safe/__init__.py
pip_safe/__main__.py
pip_safe/utils.py
pip_safe-0.0.12.dist-info/LICENSE
pip_safe-0.0.12.dist-info/METADATA
pip_safe-0.0.12.dist-info/WHEEL
pip_safe-0.0.12.dist-info/entry_points.txt
pip_safe-0.0.12.dist-info/top_level.txt
pip_safe-0.0.12.dist-info/RECORD
