Metadata-Version: 2.1
Name: pip-safe
Version: 0.0.12
Summary: A CLI tool to safely install CLI programs from PyPi
Home-page: https://github.com/dvershinin/pip-safe
Author: Danila Vershinin
Author-email: info@getpagespeed.com
License: BSD
Classifier: Intended Audience :: Developers
Classifier: Intended Audience :: System Administrators
Classifier: Operating System :: OS Independent
Classifier: Topic :: Software Development
Requires-Python: >=2.7, !=3.0.*, !=3.1.*, !=3.2.*, !=3.3.*
License-File: LICENSE
Requires-Dist: pip
Requires-Dist: tabulate
Requires-Dist: six
Provides-Extra: tests
Requires-Dist: pip ; extra == 'tests'
Requires-Dist: tabulate ; extra == 'tests'
Requires-Dist: six ; extra == 'tests'
Requires-Dist: pytest ; extra == 'tests'
Requires-Dist: flake8 ; extra == 'tests'
